sillm/__init__.py
sillm/chat.py
sillm/convert.py
sillm/download.py
sillm/dpo.py
sillm/lora.py
sillm/quantize.py
sillm/server.py
sillm/version.py
sillm/core/__init__.py
sillm/core/conversation.py
sillm/core/llm.py
sillm/core/loader.py
sillm/core/template.py
sillm/core/tokenizer.py
sillm/experimental/__init__.py
sillm/experimental/control.py
sillm/models/__init__.py
sillm/models/args.py
sillm/models/base.py
sillm/models/cohere.py
sillm/models/dbrx.py
sillm/models/gemma.py
sillm/models/llama.py
sillm/models/mixtral.py
sillm/models/phi.py
sillm/models/phi3.py
sillm/models/qwen2.py
sillm/models/starcoder2.py
sillm/templates/alpaca.jinja
sillm/templates/chatml.jinja
sillm/templates/cohere.jinja
sillm/templates/empty.jinja
sillm/templates/gemma.jinja
sillm/templates/llama2.jinja
sillm/templates/llama3.jinja
sillm/templates/llamaguard2.jinja
sillm/templates/mistral.jinja
sillm/templates/openchat.jinja
sillm/templates/phi2.jinja
sillm/templates/phi3.jinja
sillm/templates/qwen2.jinja
sillm/templates/vicuna.jinja
sillm/templates/yi.jinja
sillm/training/__init__.py
sillm/training/dataset.py
sillm/training/dpo.py
sillm/training/lora.py
sillm/utils/__init__.py
sillm/utils/common.py
sillm/utils/log.py
sillm/utils/mapping.py
sillm/utils/plot.py
sillm/utils/quantization.py
sillm_mlx-0.1.5.dist-info/LICENSE
sillm_mlx-0.1.5.dist-info/METADATA
sillm_mlx-0.1.5.dist-info/WHEEL
sillm_mlx-0.1.5.dist-info/top_level.txt
sillm_mlx-0.1.5.dist-info/RECORD
