Metadata-Version: 2.1
Name: sillm-mlx
Version: 0.1.5
Summary: Running and training LLMs on Apple Silicon via MLX
Home-page: https://github.com/armbues/SiLLM
Requires-Python: >=3.9
License-File: LICENSE
Requires-Dist: mlx >=0.14.1
Requires-Dist: transformers >=4.41.1
Requires-Dist: sentencepiece ==0.2.0
Requires-Dist: protobuf
Requires-Dist: numpy
Requires-Dist: tqdm
Requires-Dist: psutil
Requires-Dist: pyyaml
Requires-Dist: matplotlib
Requires-Dist: jinja2
Provides-Extra: server
Requires-Dist: fastapi ; extra == 'server'
Requires-Dist: uvicorn ; extra == 'server'
Requires-Dist: python-multipart ; extra == 'server'
